wikijscmd/__init__.py
wikijscmd/__main__.py
wikijscmd/app.py
wikijscmd/commands.py
wikijscmd/config.py
wikijscmd/custom_requests.py
wikijscmd/graphql_queries.py
wikijscmd/tui.py
wikijscmd/util.py
wikijscmd-0.3.0.dist-info/LICENSE
wikijscmd-0.3.0.dist-info/WHEEL
wikijscmd-0.3.0.dist-info/METADATA
wikijscmd-0.3.0.dist-info/RECORD
