Metadata-Version: 2.1
Name: wikijscmd
Version: 0.3.0
Summary: A command line interface (CLI) for wiki.js
License: GPL 3
Author: Mark Powers
Author-email: mark@marks.kitchen
Requires-Python: >=3.8,<4.0
Classifier: License :: Other/Proprietary License
Classifier: Programming Language :: Python :: 3
Classifier: Programming Language :: Python :: 3.10
Classifier: Programming Language :: Python :: 3.8
Classifier: Programming Language :: Python :: 3.9
Requires-Dist: requests (>=2.26.0,<3.0.0)
